is_ai_odd/__init__.py
is_ai_odd/api.py
is_ai_odd/main.py
is_ai_odd/validation.py
is_ai_odd-1.1.dist-info/LICENSE
is_ai_odd-1.1.dist-info/METADATA
is_ai_odd-1.1.dist-info/WHEEL
is_ai_odd-1.1.dist-info/top_level.txt
is_ai_odd-1.1.dist-info/RECORD
