Metadata-Version: 2.1
Name: is-ai-odd
Version: 1.1
Summary: A Python package that leverages AI to identify odd patterns in data using generative models.
Home-page: https://github.com/trimpta/is_ai_odd
Author: trimpta
Author-email: hi@trimpta.com
Classifier: Programming Language :: Python :: 3
Classifier: Programming Language :: Python :: 3.9
Classifier: License :: OSI Approved :: MIT License
Classifier: Operating System :: OS Independent
Requires-Python: >=3.9
License-File: LICENSE
Requires-Dist: google-generativeai
